[
null,
{"id":1,"list":[{"code":223,"indent":0,"parameters":[[102,0,0,0],15,false]},{"code":230,"indent":0,"parameters":[15]},{"code":223,"indent":0,"parameters":[[0,136,0,0],15,false]},{"code":230,"indent":0,"parameters":[15]},{"code":223,"indent":0,"parameters":[[0,0,204,0],15,false]},{"code":230,"indent":0,"parameters":[15]},{"code":223,"indent":0,"parameters":[[102,0,0,0],15,false]},{"code":230,"indent":0,"parameters":[15]},{"code":223,"indent":0,"parameters":[[0,136,0,0],15,false]},{"code":230,"indent":0,"parameters":[15]},{"code":223,"indent":0,"parameters":[[0,0,204,0],15,false]},{"code":230,"indent":0,"parameters":[15]},{"code":223,"indent":0,"parameters":[[102,0,0,0],15,false]},{"code":230,"indent":0,"parameters":[15]},{"code":223,"indent":0,"parameters":[[0,136,0,0],15,false]},{"code":230,"indent":0,"parameters":[15]},{"code":223,"indent":0,"parameters":[[0,0,204,0],15,false]},{"code":230,"indent":0,"parameters":[15]},{"code":223,"indent":0,"parameters":[[0,0,0,0],15,false]},{"code":230,"indent":0,"parameters":[15]},{"code":0,"indent":0,"parameters":[]}],"name":"Screenanimation","switchId":1,"trigger":0},
{"id":2,"list":[{"code":250,"indent":0,"parameters":[{"name":"Book1","volume":90,"pitch":100,"pan":0}]},{"code":101,"indent":0,"parameters":["Nature",4,0,2,"\\P[1]"]},{"code":401,"indent":0,"parameters":["Why would I read this garbage?"]},{"code":126,"indent":0,"parameters":[32,1,0,1]},{"code":250,"indent":0,"parameters":[{"name":"Book2","volume":45,"pitch":100,"pan":0}]},{"code":250,"indent":0,"parameters":[{"name":"Slash7","volume":40,"pitch":100,"pan":0}]},{"code":101,"indent":0,"parameters":["",0,0,2,""]},{"code":401,"indent":0,"parameters":["\\P[1] abandoned the manual..."]},{"code":0,"indent":0,"parameters":[]}],"name":"book","switchId":1,"trigger":0},
{"id":3,"list":[{"code":0,"indent":0,"parameters":[]}],"name":"","switchId":1,"trigger":0},
{"id":4,"list":[{"code":0,"indent":0,"parameters":[]}],"name":"","switchId":1,"trigger":0}
]